sawo/__init__.py
sawo/sawo.py
sawo-1.1.3.dist-info/METADATA
sawo-1.1.3.dist-info/WHEEL
sawo-1.1.3.dist-info/top_level.txt
sawo-1.1.3.dist-info/RECORD
