Metadata-Version: 2.1
Name: sawo
Version: 1.1.3
Summary: Sawo Project
Home-page: UNKNOWN
Author: Sawolab
Author-email: tech@sawolabs.com
License: MIT
Platform: UNKNOWN
Requires-Dist: bs4
